{"is_source_file": true, "format": "JSON", "description": "Configuration file for TypeScript compiler options specific to the Node environment in a Vite project.", "external_files": ["vite.config.ts"], "external_methods": [], "published": [], "classes": [], "methods": [], "calls": [], "search-terms": ["TypeScript", "compiler options", "Vite"], "state": 2, "file_id": 12, "knowledge_revision": 18, "git_revision": "42d04370267e4249c78eaf800b31a035c5c9a79c", "hash": "b39b0c04c8b06a94fa53e598a344f2b4", "format-version": 4, "code-base-name": "hello-react", "filename": "vite-project/tsconfig.node.json", "revision_history": [{"18": "42d04370267e4249c78eaf800b31a035c5c9a79c"}]}